{
    "project name": "Vatavuk_excel-io",
    "vulnerable dependencies": {
        "org.apache.poi:poi-ooxml:3.17": {
            "used-method num": 59,
            "used method": [
                "org.apache.poi.xssf.usermodel.XSSFSheet:org.apache.poi.xssf.usermodel.XSSFWorkbook getWorkbook()",
                "org.apache.poi.xssf.usermodel.XSSFWorkbook:org.apache.poi.xssf.usermodel.XSSFSheet createSheet(java.lang.String)",
                "org.apache.poi.xssf.usermodel.XSSFRow:org.apache.poi.xssf.usermodel.XSSFCell createCell(int)",
                "org.apache.poi.xssf.usermodel.XSSFCell:void setCellValue(java.lang.String)",
                "org.apache.poi.xssf.usermodel.XSSFCellStyle:void setBorderBottom(org.apache.poi.ss.usermodel.BorderStyle)",
                "org.apache.poi.xssf.usermodel.XSSFRow:void setHeightInPoints(float)",
                "org.apache.poi.xssf.usermodel.XSSFCellStyle:org.apache.poi.xssf.usermodel.XSSFFont getFont()",
                "org.apache.poi.xssf.usermodel.XSSFCellStyle:void setFont(org.apache.poi.ss.usermodel.Font)",
                "org.apache.poi.xssf.usermodel.XSSFCell:void setCellValue(double)",
                "org.apache.poi.xssf.usermodel.XSSFSheet:void setDefaultRowHeightInPoints(float)",
                "org.apache.poi.xssf.usermodel.XSSFFont:void setFontHeight(short)",
                "org.apache.poi.xssf.usermodel.XSSFFont:void setTypeOffset(short)",
                "org.apache.poi.xssf.usermodel.XSSFDialogsheet:org.apache.poi.xssf.usermodel.XSSFRow createRow(int)",
                "org.apache.poi.xssf.usermodel.XSSFRow:short getLastCellNum()",
                "org.apache.poi.xssf.usermodel.XSSFSheet:org.apache.poi.xssf.usermodel.XSSFRow getRow(int)",
                "org.apache.poi.xssf.usermodel.XSSFSheet:int getLastRowNum()",
                "org.apache.poi.xssf.usermodel.XSSFCell:org.apache.poi.xssf.usermodel.XSSFCellStyle getCellStyle()",
                "org.apache.poi.xssf.usermodel.XSSFFont:void setCharSet(byte)",
                "org.apache.poi.xssf.usermodel.XSSFCellStyle:void setRotation(short)",
                "org.apache.poi.xssf.usermodel.XSSFCellStyle:void setVerticalAlignment(org.apache.poi.ss.usermodel.VerticalAlignment)",
                "org.apache.poi.xssf.usermodel.XSSFSheet:void setDefaultRowHeight(short)",
                "org.apache.poi.xssf.usermodel.XSSFRow:org.apache.poi.xssf.usermodel.XSSFCell getCell(int)",
                "org.apache.poi.xssf.usermodel.XSSFCell:void setCellStyle(org.apache.poi.ss.usermodel.CellStyle)",
                "org.apache.poi.xssf.usermodel.XSSFSheet:void autoSizeColumn(int,boolean)",
                "org.apache.poi.xssf.usermodel.XSSFCellStyle:void setIndention(short)",
                "org.apache.poi.xssf.usermodel.XSSFCellStyle:void setWrapText(boolean)",
                "org.apache.poi.xssf.usermodel.XSSFCell:void setCellFormula(java.lang.String)",
                "org.apache.poi.xssf.usermodel.XSSFCellStyle:void setBorderLeft(org.apache.poi.ss.usermodel.BorderStyle)",
                "org.apache.poi.xssf.usermodel.XSSFWorkbook:void <clinit>()",
                "org.apache.poi.xssf.usermodel.XSSFFont:void setFontHeightInPoints(short)",
                "org.apache.poi.xssf.usermodel.XSSFWorkbook:void <init>()",
                "org.apache.poi.xssf.usermodel.XSSFSheet:void setDefaultColumnWidth(int)",
                "org.apache.poi.xssf.usermodel.XSSFSheet:void setFitToPage(boolean)",
                "org.apache.poi.xssf.usermodel.XSSFSheet:int addMergedRegion(org.apache.poi.ss.util.CellRangeAddress)",
                "org.apache.poi.xssf.usermodel.XSSFSheet:void setColumnWidth(int,int)",
                "org.apache.poi.xssf.usermodel.XSSFCellStyle:void setFillForegroundColor(short)",
                "org.apache.poi.xssf.usermodel.XSSFCellStyle:void setAlignment(org.apache.poi.ss.usermodel.HorizontalAlignment)",
                "org.apache.poi.xssf.usermodel.XSSFCellStyle:void setBorderRight(org.apache.poi.ss.usermodel.BorderStyle)",
                "org.apache.poi.xssf.usermodel.XSSFFont:void setUnderline(byte)",
                "org.apache.poi.xssf.usermodel.XSSFWorkbook$SheetIterator:org.apache.poi.ss.usermodel.Sheet next()",
                "org.apache.poi.xssf.usermodel.XSSFCell:void setCellValue(java.util.Calendar)",
                "org.apache.poi.xssf.usermodel.XSSFWorkbook:org.apache.poi.xssf.usermodel.XSSFSheet getSheetAt(int)",
                "org.apache.poi.xssf.usermodel.XSSFRow:void setHeight(short)",
                "org.apache.poi.xssf.usermodel.XSSFWorkbook:void <init>(java.io.InputStream)",
                "org.apache.poi.xssf.usermodel.XSSFWorkbook:org.apache.poi.xssf.usermodel.XSSFSheet createSheet()",
                "org.apache.poi.xssf.usermodel.XSSFCellStyle:void setFillBackgroundColor(short)",
                "org.apache.poi.xssf.usermodel.XSSFCellStyle:void setFillPattern(org.apache.poi.ss.usermodel.FillPatternType)",
                "org.apache.poi.xssf.usermodel.XSSFCell:void setCellValue(java.util.Date)",
                "org.apache.poi.xssf.usermodel.XSSFCellStyle:void setBorderTop(org.apache.poi.ss.usermodel.BorderStyle)",
                "org.apache.poi.xssf.usermodel.XSSFWorkbook$SheetIterator:boolean hasNext()",
                "org.apache.poi.POIXMLDocument:void close()",
                "org.apache.poi.xssf.usermodel.XSSFCellStyle:void setDataFormat(short)",
                "org.apache.poi.POIXMLDocument:void write(java.io.OutputStream)",
                "org.apache.poi.xssf.usermodel.XSSFFont:void setFontName(java.lang.String)",
                "org.apache.poi.xssf.usermodel.XSSFWorkbook:org.apache.poi.xssf.usermodel.XSSFCellStyle createCellStyle()",
                "org.apache.poi.xssf.usermodel.XSSFRow:org.apache.poi.xssf.usermodel.XSSFSheet getSheet()",
                "org.apache.poi.xssf.usermodel.XSSFFont:void setColor(short)",
                "org.apache.poi.xssf.usermodel.XSSFWorkbook:org.apache.poi.xssf.usermodel.XSSFSheet getSheet(java.lang.String)",
                "org.apache.poi.xssf.usermodel.XSSFFont:void setCharSet(int)"
            ]
        },
        "junit:junit:4.12": {
            "used-method num": 0,
            "used method": []
        }
    }
}