{
    "project name": "thomasdarimont_spring-boot-admin-keycloak-example",
    "modules": {
        "com.example:admin-service": {
            "vulnerable dependencies": {
                "org.jboss.resteasy:resteasy-client:3.6.1.Final": {
                    "used-method num": 0,
                    "used method": []
                }
            }
        },
        "com.example:todo-service": {
            "vulnerable dependencies": {
                "org.jboss.resteasy:resteasy-client:3.6.1.Final": {
                    "used-method num": 0,
                    "used method": []
                }
            }
        }
    }
}