{
    "project name": "yunTerry_spring-cloud-netflix",
    "modules": {
        "com.terry:eureka-server": {
            "vulnerable dependencies": {
                "org.springframework.cloud:spring-cloud-config-server:1.4.2.RELEASE": {
                    "used-method num": 0,
                    "used method": []
                }
            }
        },
        "com.terry:admin-server": {
            "vulnerable dependencies": {
                "org.springframework.cloud:spring-cloud-config-server:1.4.2.RELEASE": {
                    "used-method num": 0,
                    "used method": []
                }
            }
        },
        "com.terry:config-server": {
            "vulnerable dependencies": {
                "org.springframework.cloud:spring-cloud-config-server:1.4.2.RELEASE": {
                    "used-method num": 0,
                    "used method": []
                }
            }
        },
        "com.terry:token-service": {
            "vulnerable dependencies": {
                "org.springframework.cloud:spring-cloud-config-server:1.4.2.RELEASE": {
                    "used-method num": 0,
                    "used method": []
                }
            }
        },
        "com.terry:user-service": {
            "vulnerable dependencies": {
                "org.springframework.cloud:spring-cloud-config-server:1.4.2.RELEASE": {
                    "used-method num": 0,
                    "used method": []
                }
            }
        },
        "com.terry:zuul-gateway": {
            "vulnerable dependencies": {
                "org.springframework.cloud:spring-cloud-config-server:1.4.2.RELEASE": {
                    "used-method num": 0,
                    "used method": []
                }
            }
        },
        "com.terry:hystrix-turbine": {
            "vulnerable dependencies": {
                "org.springframework.cloud:spring-cloud-config-server:1.4.2.RELEASE": {
                    "used-method num": 0,
                    "used method": []
                }
            }
        },
        "com.terry:zipkin": {
            "vulnerable dependencies": {
                "org.springframework.cloud:spring-cloud-config-server:1.4.2.RELEASE": {
                    "used-method num": 0,
                    "used method": []
                }
            }
        }
    }
}