{
    "project name": "lyubomyr-shaydariv_ant-shade-task",
    "vulnerable dependencies": {
        "org.apache.ant:ant:1.9.7": {
            "used-method num": 4,
            "used method": [
                "org.apache.tools.ant.BuildException:void <init>(java.lang.Throwable)",
                "org.apache.tools.ant.BuildException:void <init>(java.lang.String)",
                "org.apache.tools.ant.Task:void <init>()",
                "org.apache.tools.ant.util.VectorSet:boolean add(java.lang.Object)"
            ]
        }
    }
}